README.rst
setup.py
src/zs/__init__.py
src/zs.bibtex.egg-info/PKG-INFO
src/zs.bibtex.egg-info/SOURCES.txt
src/zs.bibtex.egg-info/dependency_links.txt
src/zs.bibtex.egg-info/namespace_packages.txt
src/zs.bibtex.egg-info/pbr.json
src/zs.bibtex.egg-info/requires.txt
src/zs.bibtex.egg-info/top_level.txt
src/zs/bibtex/__init__.py
src/zs/bibtex/exceptions.py
src/zs/bibtex/parser.py
src/zs/bibtex/structures.py