Metadata-Version: 1.1
Name: zs.bibtex
Version: 1.0.0rc1
Summary: A small collection of bibtex utilities (incl. a minimal parser)
Home-page: https://github.com/zerok/zs.bibtex/
Author: Horst Gutmann
Author-email: zerok@zerokspot.com
License: BSD
Platform: UNKNOWN
Classifier: Programming Language :: Python :: 2.7
Classifier: Programming Language :: Python :: 3.4
Classifier: Development Status :: 3 - Alpha
Classifier: Intended Audience :: Developers
Classifier: Programming Language :: Python
Classifier: Topic :: Software Development :: Libraries :: Python Modules
Classifier: License :: OSI Approved :: BSD License
